quantllm/__init__.py
quantllm/utils.py
quantllm/cli/__init__.py
quantllm/cli/commands.py
quantllm/cli/parser.py
quantllm/config/__init__.py
quantllm/config/config_manager.py
quantllm/config/dataset_config.py
quantllm/config/model_config.py
quantllm/config/training_config.py
quantllm/data/__init__.py
quantllm/data/dataloader.py
quantllm/data/dataset_preprocessor.py
quantllm/data/dataset_splitter.py
quantllm/data/load_dataset.py
quantllm/hub/__init__.py
quantllm/hub/checkpoint_manager.py
quantllm/hub/hub_manager.py
quantllm/model/__init__.py
quantllm/model/lora_config.py
quantllm/model/model.py
quantllm/trainer/__init__.py
quantllm/trainer/evaluator.py
quantllm/trainer/logger.py
quantllm/trainer/trainer.py
quantllm/utils/__init__.py
quantllm/utils/log_config.py
quantllm/utils/optimizations.py
quantllm-1.0.0.dist-info/METADATA
quantllm-1.0.0.dist-info/WHEEL
quantllm-1.0.0.dist-info/top_level.txt
quantllm-1.0.0.dist-info/RECORD
