Metadata-Version: 2.4
Name: quantllm
Version: 1.0.0
Summary: A lightweight library for quantized LLM fine-tuning and deployment
Author: Dark Coder
Author-email: codewithdark90@gmail.com
Project-URL: Homepage, https://github.com/codewithdark-git/DiffusionLM
Project-URL: Sponsor, https://github.com/sponsors/codewithdark-git
Classifier: Development Status :: 3 - Alpha
Classifier: Intended Audience :: Science/Research
Classifier: License :: OSI Approved :: MIT License
Classifier: Operating System :: OS Independent
Classifier: Programming Language :: Python :: 3
Classifier: Programming Language :: Python :: 3.10
Classifier: Programming Language :: Python :: 3.11
Classifier: Topic :: Scientific/Engineering :: Artificial Intelligence
Requires-Python: >=3.10
Requires-Dist: torch>=2.0.0
Requires-Dist: transformers>=4.30.0
Requires-Dist: datasets>=2.12.0
Requires-Dist: accelerate>=0.20.0
Requires-Dist: peft>=0.4.0
Requires-Dist: bitsandbytes>=0.40.0
Requires-Dist: scipy>=1.10.0
Requires-Dist: scikit-learn>=1.0.0
Requires-Dist: tqdm>=4.65.0
Requires-Dist: numpy>=1.24.0
Requires-Dist: wandb>=0.15.0
Requires-Dist: sentencepiece>=0.1.99
Requires-Dist: protobuf>=3.20.0
Requires-Dist: einops>=0.6.1
Requires-Dist: evaluate>=0.4.0
Requires-Dist: tensorboard>=2.13.0
Provides-Extra: dev
Requires-Dist: sphinx>=4.5.0; extra == "dev"
Requires-Dist: sphinx-rtd-theme>=1.0.0; extra == "dev"
Requires-Dist: sphinx-copybutton>=0.5.0; extra == "dev"
Requires-Dist: sphinx-autodoc-typehints>=1.18.3; extra == "dev"
Requires-Dist: myst-parser>=0.18.1; extra == "dev"
Requires-Dist: pytest>=7.0.0; extra == "dev"
Requires-Dist: pytest-cov>=3.0.0; extra == "dev"
Requires-Dist: black>=22.0.0; extra == "dev"
Requires-Dist: isort>=5.10.0; extra == "dev"
Requires-Dist: flake8>=4.0.0; extra == "dev"
Dynamic: author
Dynamic: author-email
Dynamic: classifier
Dynamic: description
Dynamic: description-content-type
Dynamic: project-url
Dynamic: provides-extra
Dynamic: requires-dist
Dynamic: requires-python
Dynamic: summary
